minha_biblioteca/__init__.py
minha_biblioteca/modulo1.py
minha_biblioteca_humb-1.0.1.dist-info/METADATA
minha_biblioteca_humb-1.0.1.dist-info/WHEEL
minha_biblioteca_humb-1.0.1.dist-info/top_level.txt
minha_biblioteca_humb-1.0.1.dist-info/RECORD
