Metadata-Version: 2.1
Name: minha-biblioteca-humb
Version: 1.0.1
Summary: Uma bilioteca python
Author: Humberto
License: UNKNOWN
Platform: UNKNOWN
